textblob_nl/__init__.py
textblob_nl/_text.py
textblob_nl/compat.py
textblob_nl/inflect.py
textblob_nl/nl-context.txt
textblob_nl/nl-lexicon.txt
textblob_nl/nl-morphology.txt
textblob_nl/nl-sentiment.xml
textblob_nl/nl-verbs.txt
textblob_nl/nl.py
textblob_nl/sentiments.py
textblob_nl/taggers.py
textblob_nl-0.0.1.dist-info/AUTHORS.rst
textblob_nl-0.0.1.dist-info/LICENSE
textblob_nl-0.0.1.dist-info/METADATA
textblob_nl-0.0.1.dist-info/NOTICE
textblob_nl-0.0.1.dist-info/WHEEL
textblob_nl-0.0.1.dist-info/top_level.txt
textblob_nl-0.0.1.dist-info/RECORD
