Metadata-Version: 2.1
Name: textblob-nl
Version: 0.0.1
Summary: Dutch language support for TextBlob.
Home-page: https://github.com/gvisniuc/textblob-nl
Author: George Visniuc
Author-email: georgevisniuc@gmail.com
License: Copyright 2013 Steven Loria
Requires-Dist: textblob (>=0.8.0)
